text_to_struct/__init__.py
text_to_struct/main.py
text_to_struct/prompts.py
text_to_struct-2025.12.22084055.dist-info/METADATA
text_to_struct-2025.12.22084055.dist-info/WHEEL
text_to_struct-2025.12.22084055.dist-info/top_level.txt
text_to_struct-2025.12.22084055.dist-info/RECORD
