Metadata-Version: 2.4
Name: text-to-struct
Version: 2025.12.22084055
Summary: text-to-struct converts unstructured text into standardized, structured output
Author-email: text-to-struct <hi@eugene.plus>
License: MIT
Project-URL: Homepage, https://github.com/chigwell/text-to-struct
Requires-Python: >=3.9
Requires-Dist: langchain-llm7>=0.0.0
Requires-Dist: llmatch-messages>=0.0.0
Requires-Dist: langchain-core>=0.3.0
